{
  "_note": "death-guard vehicles \u2014 generated from BSData + MFM",
  "_source": "BSData 11e + MFM (auto-generated)",
  "Chaos Land Raider": {
    "pts": 220,
    "ranged": [
      {
        "name": "Soulshatter lascannon",
        "unit_name": "Chaos Land Raider"
      },
      {
        "name": "Havoc launcher",
        "unit_name": "Chaos Land Raider"
      },
      {
        "name": "Twin heavy bolter",
        "unit_name": "Chaos Land Raider"
      },
      {
        "name": "Combi-bolter",
        "unit_name": "Chaos Land Raider"
      },
      {
        "name": "Combi-weapon",
        "unit_name": "Chaos Land Raider"
      }
    ],
    "melee": [
      {
        "name": "Armoured tracks",
        "unit_name": "Chaos Land Raider"
      }
    ],
    "innate": [],
    "info": {
      "M": "10\"",
      "T": 12,
      "SV": 2,
      "W": 16,
      "OC": 5
    }
  },
  "Chaos Predator Annihilator": {
    "pts": 135,
    "ranged": [
      {
        "name": "Predator twin lascannon",
        "unit_name": "Chaos Predator Annihilator"
      },
      {
        "name": "Havoc launcher",
        "unit_name": "Chaos Predator Annihilator"
      },
      {
        "name": "Combi-bolter",
        "unit_name": "Chaos Predator Annihilator"
      },
      {
        "name": "Combi-weapon",
        "unit_name": "Chaos Predator Annihilator"
      },
      {
        "name": "Heavy bolter",
        "unit_name": "Chaos Predator Annihilator"
      },
      {
        "name": "Lascannon",
        "unit_name": "Chaos Predator Annihilator"
      }
    ],
    "melee": [
      {
        "name": "Armoured tracks",
        "unit_name": "Chaos Predator Annihilator"
      }
    ],
    "innate": [],
    "info": {
      "M": "10\"",
      "T": 10,
      "SV": 3,
      "W": 11,
      "OC": 3
    }
  },
  "Chaos Predator Destructor": {
    "pts": 145,
    "ranged": [
      {
        "name": "Predator autocannon",
        "unit_name": "Chaos Predator Destructor"
      },
      {
        "name": "Havoc launcher",
        "unit_name": "Chaos Predator Destructor"
      },
      {
        "name": "Combi-bolter",
        "unit_name": "Chaos Predator Destructor"
      },
      {
        "name": "Combi-weapon",
        "unit_name": "Chaos Predator Destructor"
      },
      {
        "name": "Heavy bolter",
        "unit_name": "Chaos Predator Destructor"
      },
      {
        "name": "Lascannon",
        "unit_name": "Chaos Predator Destructor"
      }
    ],
    "melee": [
      {
        "name": "Armoured tracks",
        "unit_name": "Chaos Predator Destructor"
      }
    ],
    "innate": [],
    "info": {
      "M": "10\"",
      "T": 10,
      "SV": 3,
      "W": 11,
      "OC": 3
    }
  },
  "Chaos Rhino": {
    "pts": 85,
    "ranged": [
      {
        "name": "Combi-bolter",
        "unit_name": "Chaos Rhino"
      },
      {
        "name": "Havoc launcher",
        "unit_name": "Chaos Rhino"
      },
      {
        "name": "Combi-weapon",
        "unit_name": "Chaos Rhino"
      }
    ],
    "melee": [
      {
        "name": "Armoured tracks",
        "unit_name": "Chaos Rhino"
      }
    ],
    "innate": [],
    "info": {
      "M": "12\"",
      "T": 9,
      "SV": 3,
      "W": 10,
      "OC": 2
    }
  },
  "Defiler": {
    "pts": 290,
    "ranged": [
      {
        "name": "Heavy missile launcher - frag",
        "unit_name": "Defiler"
      },
      {
        "name": "Heavy missile launcher - krak",
        "unit_name": "Defiler"
      },
      {
        "name": "Hades lascannon",
        "unit_name": "Defiler"
      },
      {
        "name": "Heavy reaper autocannon",
        "unit_name": "Defiler"
      },
      {
        "name": "Hades battle cannon",
        "unit_name": "Defiler"
      },
      {
        "name": "Ectoplasma destructor",
        "unit_name": "Defiler"
      },
      {
        "name": "Heavy baleflamer",
        "unit_name": "Defiler"
      },
      {
        "name": "Excruciator cannon",
        "unit_name": "Defiler"
      },
      {
        "name": "Magma cutter",
        "unit_name": "Defiler"
      }
    ],
    "melee": [
      {
        "name": "Shearing claws - strike",
        "unit_name": "Defiler"
      },
      {
        "name": "Shearing claws - sweep",
        "unit_name": "Defiler"
      },
      {
        "name": "Electroscourge",
        "unit_name": "Defiler"
      }
    ],
    "innate": [],
    "info": {
      "M": "12\"",
      "T": 11,
      "SV": 3,
      "W": 18,
      "OC": 5,
      "INV": 5
    }
  },
  "Foetid Bloat-Drone": {
    "pts": 100,
    "ranged": [
      {
        "name": "Plaguespitter",
        "unit_name": "Foetid Bloat-Drone"
      }
    ],
    "melee": [
      {
        "name": "Plague probe",
        "unit_name": "Foetid Bloat-Drone"
      },
      {
        "name": "Fleshmower",
        "unit_name": "Foetid Bloat-Drone"
      }
    ],
    "innate": [],
    "info": {
      "M": "10\"",
      "T": 9,
      "SV": 3,
      "W": 10,
      "OC": 3,
      "INV": 5
    }
  },
  "Foetid Bloat-Drone With Heavy Blight Launcher": {
    "pts": 125,
    "ranged": [
      {
        "name": "Heavy blight launcher",
        "unit_name": "Foetid Bloat-Drone With Heavy Blight Launcher"
      }
    ],
    "melee": [
      {
        "name": "Plague probe",
        "unit_name": "Foetid Bloat-Drone With Heavy Blight Launcher"
      }
    ],
    "innate": [],
    "info": {
      "M": "10\"",
      "T": 9,
      "SV": 3,
      "W": 10,
      "OC": 3,
      "INV": 5
    }
  },
  "Helbrute": {
    "pts": 110,
    "ranged": [
      {
        "name": "Combi-bolter",
        "unit_name": "Helbrute"
      },
      {
        "name": "Heavy flamer",
        "unit_name": "Helbrute"
      },
      {
        "name": "Missile launcher - frag",
        "unit_name": "Helbrute"
      },
      {
        "name": "Missile launcher - krak",
        "unit_name": "Helbrute"
      },
      {
        "name": "Multi-melta",
        "unit_name": "Helbrute"
      },
      {
        "name": "Twin autocannon",
        "unit_name": "Helbrute"
      },
      {
        "name": "Plasma cannon",
        "unit_name": "Helbrute"
      },
      {
        "name": "Twin heavy bolter",
        "unit_name": "Helbrute"
      },
      {
        "name": "Twin lascannon",
        "unit_name": "Helbrute"
      }
    ],
    "melee": [
      {
        "name": "Close combat weapon",
        "unit_name": "Helbrute"
      },
      {
        "name": "Helbrute fist",
        "unit_name": "Helbrute"
      },
      {
        "name": "Power scourge",
        "unit_name": "Helbrute"
      },
      {
        "name": "Helbrute hammer",
        "unit_name": "Helbrute"
      }
    ],
    "innate": [],
    "info": {
      "M": "7\"",
      "T": 9,
      "SV": 2,
      "W": 8,
      "OC": 3
    }
  },
  "Myphitic Blight-hauler": {
    "pts": 100,
    "ranged": [
      {
        "name": "Bile spurt",
        "unit_name": "Myphitic Blight-hauler"
      },
      {
        "name": "Missile launcher - frag",
        "unit_name": "Myphitic Blight-hauler"
      },
      {
        "name": "Missile launcher - krak",
        "unit_name": "Myphitic Blight-hauler"
      },
      {
        "name": "Multi-melta",
        "unit_name": "Myphitic Blight-hauler"
      }
    ],
    "melee": [
      {
        "name": "Gnashing maw",
        "unit_name": "Myphitic Blight-hauler"
      }
    ],
    "innate": [],
    "info": {
      "M": "10\"",
      "T": 9,
      "SV": 3,
      "W": 10,
      "OC": 3,
      "INV": 5
    }
  },
  "Plagueburst Crawler": {
    "pts": 185,
    "ranged": [
      {
        "name": "Plagueburst mortar",
        "unit_name": "Plagueburst Crawler"
      },
      {
        "name": "Rothail volley gun",
        "unit_name": "Plagueburst Crawler"
      },
      {
        "name": "Heavy slugger",
        "unit_name": "Plagueburst Crawler"
      },
      {
        "name": "Entropy cannon",
        "unit_name": "Plagueburst Crawler"
      },
      {
        "name": "Plaguespitter",
        "unit_name": "Plagueburst Crawler"
      }
    ],
    "melee": [
      {
        "name": "Armoured tracks",
        "unit_name": "Plagueburst Crawler"
      }
    ],
    "innate": [],
    "info": {
      "M": "10\"",
      "T": 10,
      "SV": 2,
      "W": 12,
      "OC": 3,
      "INV": 5
    }
  }
}
