{
  "_note": "Adeptus Mechanicus detachment modifiers — auto-generated from MFM",
  "_source": "BSData 11e + MFM (auto-generated)",
  "detachments": {
    "Cohort Acquisitus": {
      "objective": "RECONNAISSANCE",
      "_source": "MFM (auto-generated)",
      "choices": [
        {
          "name": "Cohort Acquisitus disposition",
          "affects": "mob",
          "_source": "MFM disposition objective",
          "description": "Detachment favours reconnaissance play"
        }
      ]
    },
    "Cohort Cybernetica": {
      "objective": "TAKE AND HOLD",
      "_source": "MFM (auto-generated)",
      "choices": [
        {
          "name": "Cohort Cybernetica disposition",
          "affects": "obj",
          "_source": "MFM disposition objective",
          "description": "Detachment favours take and hold play"
        }
      ]
    },
    "Data-Psalm Conclave": {
      "objective": "DISRUPTION",
      "_source": "MFM (auto-generated)",
      "choices": [
        {
          "name": "Data-Psalm Conclave disposition",
          "affects": "mob",
          "_source": "MFM disposition objective",
          "description": "Detachment favours disruption play"
        }
      ]
    },
    "Eradication Cohort": {
      "objective": "PURGE THE FOE",
      "_source": "MFM (auto-generated)",
      "choices": [
        {
          "name": "Eradication Cohort disposition",
          "affects": "dpp",
          "_source": "MFM disposition objective",
          "description": "Detachment favours purge the foe play"
        }
      ]
    },
    "Explorator Maniple": {
      "objective": "PRIORITY ASSETS",
      "_source": "MFM (auto-generated)",
      "choices": [
        {
          "name": "Explorator Maniple disposition",
          "affects": "dpp",
          "_source": "MFM disposition objective",
          "description": "Detachment favours priority assets play"
        }
      ]
    },
    "Haloscreed Battle Clade": {
      "objective": "PURGE THE FOE",
      "_source": "MFM (auto-generated)",
      "choices": [
        {
          "name": "Haloscreed Battle Clade disposition",
          "affects": "dpp",
          "_source": "MFM disposition objective",
          "description": "Detachment favours purge the foe play"
        }
      ]
    },
    "Lords Of The Forge": {
      "objective": "PRIORITY ASSETS",
      "_source": "MFM (auto-generated)",
      "choices": [
        {
          "name": "Lords Of The Forge disposition",
          "affects": "dpp",
          "_source": "MFM disposition objective",
          "description": "Detachment favours priority assets play"
        }
      ]
    },
    "Luminen Auto-Choir": {
      "objective": "DISRUPTION",
      "_source": "MFM (auto-generated)",
      "choices": [
        {
          "name": "Luminen Auto-Choir disposition",
          "affects": "mob",
          "_source": "MFM disposition objective",
          "description": "Detachment favours disruption play"
        }
      ]
    },
    "Rad-Zone Corps": {
      "objective": "TAKE AND HOLD",
      "_source": "MFM (auto-generated)",
      "choices": [
        {
          "name": "Rad-Zone Corps disposition",
          "affects": "obj",
          "_source": "MFM disposition objective",
          "description": "Detachment favours take and hold play"
        }
      ]
    },
    "Skitarii Hunter Cohort": {
      "objective": "RECONNAISSANCE",
      "_source": "MFM (auto-generated)",
      "choices": [
        {
          "name": "Skitarii Hunter Cohort disposition",
          "affects": "mob",
          "_source": "MFM disposition objective",
          "description": "Detachment favours reconnaissance play"
        }
      ]
    }
  }
}
