{
  "Skull Cannon": {
    "pts": 90,
    "ranged": [
      {
        "name": "Skull cannon",
        "unit_name": "Skull Cannon"
      }
    ],
    "melee": [
      {
        "name": "Biting maw",
        "unit_name": "Skull Cannon"
      },
      {
        "name": "Attendant's hellblades",
        "unit_name": "Skull Cannon"
      }
    ],
    "innate": [],
    "info": {
      "M": "8\"",
      "T": 9,
      "SV": 4,
      "W": 9,
      "OC": 3,
      "INV": 4,
      "deep_strike": true
    }
  },
  "Burning Chariot": {
    "pts": 115,
    "ranged": [
      {
        "name": "Fires of Tzeentch - blue fire",
        "unit_name": "Burning Chariot"
      },
      {
        "name": "Fires of Tzeentch - pink fire",
        "unit_name": "Burning Chariot"
      }
    ],
    "melee": [
      {
        "name": "Flamer mouths",
        "unit_name": "Burning Chariot"
      },
      {
        "name": "Screamer bites",
        "unit_name": "Burning Chariot"
      }
    ],
    "innate": [],
    "info": {
      "M": "12\"",
      "T": 8,
      "SV": 7,
      "W": 9,
      "OC": 3,
      "INV": 4,
      "deep_strike": true
    }
  },
  "Soul Grinder": {
    "pts": 180,
    "ranged": [
      {
        "name": "Harvester cannon",
        "unit_name": "Soul Grinder"
      }
    ],
    "melee": [
      {
        "name": "Iron claw",
        "unit_name": "Soul Grinder"
      }
    ],
    "innate": [],
    "info": {
      "M": "8\"",
      "T": 11,
      "SV": 3,
      "W": 14,
      "OC": 5,
      "INV": 4
    },
    "pts_3rd": 195
  },
  "Skull Altar": {
    "pts": 105,
    "ranged": [],
    "melee": [],
    "innate": [],
    "info": {
      "M": "-",
      "T": 12,
      "SV": 3,
      "W": 10,
      "OC": 0,
      "INV": null
    }
  },
  "Feculent Gnarlmaw": {
    "pts": 100,
    "ranged": [],
    "melee": [],
    "innate": [],
    "info": {
      "M": "-",
      "T": 9,
      "SV": 4,
      "W": 9,
      "OC": 0,
      "INV": null
    }
  }
}
