{
  "_note": "Thousand Sons detachment modifiers — auto-generated from MFM",
  "_source": "BSData 11e + MFM (auto-generated)",
  "detachments": {
    "Changehost Of Deceit": {
      "objective": "RECONNAISSANCE",
      "_source": "MFM (auto-generated)",
      "choices": [
        {
          "name": "Changehost Of Deceit disposition",
          "affects": "mob",
          "_source": "MFM disposition objective",
          "description": "Detachment favours reconnaissance play"
        }
      ]
    },
    "Grand Coven": {
      "objective": "PRIORITY ASSETS",
      "_source": "MFM (auto-generated)",
      "choices": [
        {
          "name": "Grand Coven disposition",
          "affects": "dpp",
          "_source": "MFM disposition objective",
          "description": "Detachment favours priority assets play"
        }
      ]
    },
    "Hexwarp Thrallband": {
      "objective": "TAKE AND HOLD",
      "_source": "MFM (auto-generated)",
      "choices": [
        {
          "name": "Hexwarp Thrallband disposition",
          "affects": "obj",
          "_source": "MFM disposition objective",
          "description": "Detachment favours take and hold play"
        }
      ]
    },
    "Ritual Of Regeneration": {
      "objective": "PURGE THE FOE",
      "_source": "MFM (auto-generated)",
      "choices": [
        {
          "name": "Ritual Of Regeneration disposition",
          "affects": "dpp",
          "_source": "MFM disposition objective",
          "description": "Detachment favours purge the foe play"
        }
      ]
    },
    "Rubricae Phalanx": {
      "objective": "TAKE AND HOLD",
      "_source": "MFM (auto-generated)",
      "choices": [
        {
          "name": "Rubricae Phalanx disposition",
          "affects": "obj",
          "_source": "MFM disposition objective",
          "description": "Detachment favours take and hold play"
        }
      ]
    },
    "Sekhetar Cohort": {
      "objective": "PRIORITY ASSETS",
      "_source": "MFM (auto-generated)",
      "choices": [
        {
          "name": "Sekhetar Cohort disposition",
          "affects": "dpp",
          "_source": "MFM disposition objective",
          "description": "Detachment favours priority assets play"
        }
      ]
    },
    "Servants Of Change": {
      "objective": "RECONNAISSANCE",
      "_source": "MFM (auto-generated)",
      "choices": [
        {
          "name": "Servants Of Change disposition",
          "affects": "mob",
          "_source": "MFM disposition objective",
          "description": "Detachment favours reconnaissance play"
        }
      ]
    },
    "Warpforged Cabal": {
      "objective": "DISRUPTION",
      "_source": "MFM (auto-generated)",
      "choices": [
        {
          "name": "Warpforged Cabal disposition",
          "affects": "mob",
          "_source": "MFM disposition objective",
          "description": "Detachment favours disruption play"
        }
      ]
    },
    "Warpmeld Pact": {
      "objective": "PURGE THE FOE",
      "_source": "MFM (auto-generated)",
      "choices": [
        {
          "name": "Warpmeld Pact disposition",
          "affects": "dpp",
          "_source": "MFM disposition objective",
          "description": "Detachment favours purge the foe play"
        }
      ]
    }
  }
}
