{
  "_note": "imperial-knights vehicles — generated from BSData + MFM",
  "_source": "BSData 11e + MFM (auto-generated)",
  "Acastus Knight Asterius": {
    "pts": 785,
    "ranged": [
      {
        "name": "Twin conversion beam cannon",
        "unit_name": "Acastus Knight Asterius"
      },
      {
        "name": "Asterius volkite culverin",
        "unit_name": "Acastus Knight Asterius"
      },
      {
        "name": "Karacnos mortar battery",
        "unit_name": "Acastus Knight Asterius"
      }
    ],
    "melee": [
      {
        "name": "Titanic feet",
        "unit_name": "Acastus Knight Asterius"
      }
    ],
    "innate": [],
    "info": {
      "M": "8\"",
      "T": 13,
      "SV": 2,
      "W": 30,
      "OC": 10,
      "INV": 5
    }
  },
  "Acastus Knight Porphyrion": {
    "pts": 725,
    "ranged": [
      {
        "name": "Twin magna lascannon",
        "unit_name": "Acastus Knight Porphyrion"
      }
    ],
    "melee": [
      {
        "name": "Titanic feet",
        "unit_name": "Acastus Knight Porphyrion"
      }
    ],
    "innate": [],
    "info": {
      "M": "8\"",
      "T": 13,
      "SV": 2,
      "W": 30,
      "OC": 10,
      "INV": 5
    }
  },
  "Armiger Helverin": {
    "pts": 140,
    "ranged": [
      {
        "name": "Armiger autocannon",
        "unit_name": "Armiger Helverin"
      }
    ],
    "melee": [
      {
        "name": "Armoured feet",
        "unit_name": "Armiger Helverin"
      }
    ],
    "innate": [],
    "info": {
      "M": "12\"",
      "T": 9,
      "SV": 3,
      "W": 14,
      "OC": 6,
      "INV": 5
    }
  },
  "Armiger Moirax": {
    "pts": 150,
    "ranged": [],
    "melee": [
      {
        "name": "Armoured feet",
        "unit_name": "Armiger Moirax"
      }
    ],
    "innate": [],
    "info": {
      "M": "12\"",
      "T": 9,
      "SV": 3,
      "W": 14,
      "OC": 6,
      "INV": 5
    }
  },
  "Armiger Warglaive": {
    "pts": 140,
    "ranged": [
      {
        "name": "Thermal spear",
        "unit_name": "Armiger Warglaive"
      }
    ],
    "melee": [
      {
        "name": "Reaper chain-cleaver - strike",
        "unit_name": "Armiger Warglaive"
      },
      {
        "name": "Reaper chain-cleaver - sweep",
        "unit_name": "Armiger Warglaive"
      }
    ],
    "innate": [],
    "info": {
      "M": "12\"",
      "T": 9,
      "SV": 3,
      "W": 14,
      "OC": 6,
      "INV": 5
    }
  }
}
